wbreport/__init__.py
wbreport/admin.py
wbreport/apps.py
wbreport/dynamic_preferences_registry.py
wbreport/filters.py
wbreport/mixins.py
wbreport/models.py
wbreport/serializers.py
wbreport/tasks.py
wbreport/urls.py
wbreport/urls_public.py
wbreport/defaults/__init__.py
wbreport/defaults/factsheets/__init__.py
wbreport/defaults/factsheets/base.py
wbreport/defaults/factsheets/menu.py
wbreport/defaults/factsheets/mixins.py
wbreport/defaults/factsheets/multitheme.py
wbreport/factories/__init__.py
wbreport/factories/data_classes.py
wbreport/factories/reports.py
wbreport/fixtures/wbreport.yaml
wbreport/migrations/0001_initial_squashed_squashed_0007_report_key.py
wbreport/migrations/0008_alter_report_file_content_type.py
wbreport/migrations/0009_alter_report_color_palette.py
wbreport/migrations/0010_auto_20240103_0947.py
wbreport/migrations/0011_auto_20240207_1629.py
wbreport/migrations/0012_reportversion_lock.py
wbreport/migrations/0013_alter_reportversion_context.py
wbreport/migrations/0014_alter_reportcategory_options_and_more.py
wbreport/migrations/__init__.py
wbreport/pdf/__init__.py
wbreport/pdf/charts/__init__.py
wbreport/pdf/charts/legend.py
wbreport/pdf/charts/pie.py
wbreport/pdf/charts/timeseries.py
wbreport/pdf/flowables/risk.py
wbreport/pdf/flowables/textboxes.py
wbreport/pdf/flowables/themes.py
wbreport/pdf/sandbox/__init__.py
wbreport/pdf/sandbox/run.py
wbreport/pdf/sandbox/templates/__init__.py
wbreport/pdf/sandbox/templates/basic_factsheet.py
wbreport/pdf/sandbox/templates/fund_factsheet.py
wbreport/pdf/sandbox/templates/long_industry_exposure_factsheet.py
wbreport/pdf/sandbox/templates/multistrat_factsheet.py
wbreport/pdf/sandbox/templates/testfile.pdf
wbreport/pdf/tables/__init__.py
wbreport/pdf/tables/aggregated_tables.py
wbreport/pdf/tables/data_tables.py
wbreport/templates/__init__.py
wbreport/templatetags/__init__.py
wbreport/templatetags/portfolio_tags.py
wbreport/tests/__init__.py
wbreport/tests/conftest.py
wbreport/tests/test_models.py
wbreport-2.2.6.dist-info/METADATA
wbreport-2.2.6.dist-info/WHEEL
wbreport-2.2.6.dist-info/licenses/LICENSE
wbreport-2.2.6.dist-info/RECORD
