Metadata-Version: 2.4
Name: wbreport
Version: 2.2.6
Author-email: Christopher Wittlinger <c.wittlinger@stainly.com>
License-File: LICENSE
Requires-Dist: wbcore
Requires-Dist: wbmailing
